csv_gp-0.2.1.dist-info/METADATA
csv_gp-0.2.1.dist-info/WHEEL
csv_gp-0.2.1.dist-info/license_files/LICENSE
README.md
LICENSE
csv_gp/__init__.py
csv_gp/__init__.pyi
csv_gp/py.typed
csv_gp/csv_gp.abi3.so
csv_gp-0.2.1.dist-info/RECORD
