Metadata-Version: 2.1
Name: csv-gp
Version: 0.2.1
Classifier: Programming Language :: Rust
Classifier: Programming Language :: Python :: Implementation :: CPython
Classifier: Programming Language :: Python :: Implementation :: PyPy
Classifier: Programming Language :: Python
Classifier: Programming Language :: Python :: 3
Classifier: Programming Language :: Python :: 3.8
Classifier: Programming Language :: Python :: 3.9
Classifier: Programming Language :: Python :: 3.10
Classifier: Programming Language :: Python :: 3.11
Classifier: Programming Language :: Python :: 3.12
Classifier: Development Status :: 5 - Production/Stable
Classifier: License :: OSI Approved :: MIT License
License-File: LICENSE
Summary: CSV GP allows you to pinpoint these common issues with a CSV file, as well as export just the parsable lines from a file.
Keywords: rust,csv
Requires-Python: >=3.8
Project-URL: Repository, https://github.com/xelixdev/csv-gp
